landpy/Debugger.py
landpy/__init__.py
landpy-0.0.1.1.dist-info/LICENSE
landpy-0.0.1.1.dist-info/METADATA
landpy-0.0.1.1.dist-info/WHEEL
landpy-0.0.1.1.dist-info/top_level.txt
landpy-0.0.1.1.dist-info/RECORD
